dozenal/__init__.py
dozenal/core.py
dozenal-0.1.0.dist-info/METADATA
dozenal-0.1.0.dist-info/WHEEL
dozenal-0.1.0.dist-info/top_level.txt
dozenal-0.1.0.dist-info/RECORD
