Metadata-Version: 2.4
Name: dozenal
Version: 0.1.0
Summary: A Python package for handling the Dozenal (base 12) system.
Author: Your Name
Requires-Python: >=3.6
Dynamic: author
Dynamic: requires-python
Dynamic: summary
